Metadata-Version: 2.1
Name: openvk
Version: 1.3
Summary: ('Python module for writing scripts for project management platform', 'OpenVK (openvk.su API wrapper)')
Home-page: https://github.com/Parliskaya/openvkapi
Author: Parliskaya
Author-email: alonaparlis@gmail.com
License: MIT License, see LICENSE file
Download-URL: https://github.com/Parliskaya/openvkapi/archive/v1.3.zip
Platform: UNKNOWN
Classifier: License :: OSI Approved :: MIT License
Classifier: Operating System :: OS Independent
Classifier: Intended Audience :: End Users/Desktop
Classifier: Intended Audience :: Developers
Classifier: Programming Language :: Python
Classifier: Programming Language :: Python :: 3
Classifier: Programming Language :: Python :: 3.8
Classifier: Programming Language :: Python :: Implementation :: PyPy
Classifier: Programming Language :: Python :: Implementation :: CPython
